[{"title":"2021高燃征兵海报","category":"社会  ","description":"#2021高燃征兵海报#↓↓↓感受当兵后的精气神！热血军营，等你加入！ ​​​​","url":"https://m.weibo.cn/search?containerid=100103type%3D1%26t%3D10%26q%3D%232021%E9%AB%98%E7%87%83%E5%BE%81%E5%85%B5%E6%B5%B7%E6%8A%A5%23&isnewpage=1&extparam=seat%3D1%26pos%3D0%26dgr%3D0%26c_type%3D51%26filter_type%3Drealtimehot%26cate%3D10103%26display_time%3D1617948744&luicode=10000011&lfid=106003type%3D25%26t%3D3%26disable_hot%3D1%26filter_type%3Drealtimehot","ads":false},{"title":"林依晨发长文回应","category":"明星-港台  ","description":"林依晨发长文回应“六点半起床做早餐、送公公上班”等传闻，表示早餐都是婆婆做的，自己已经睡觉睡到自然醒很久了。","url":"https://m.weibo.cn/search?containerid=100103type%3D1%26t%3D10%26q%3D%23%E6%9E%97%E4%BE%9D%E6%99%A8%E5%8F%91%E9%95%BF%E6%96%87%E5%9B%9E%E5%BA%94%23&isnewpage=1&extparam=seat%3D1%26filter_type%3Drealtimehot%26dgr%3D0%26cate%3D0%26pos%3D0%26realpos%3D1%26flag%3D16%26c_type%3D31%26display_time%3D1617948744&luicode=10000011&lfid=106003type%3D25%26t%3D3%26disable_hot%3D1%26filter_type%3Drealtimehot","hot":3085463,"ads":false},{"title":"女子剪掉全球最长指甲","category":"社会  ","description":"4月8日，据美国媒体报道，美国得州女子阿安娜·威廉姆斯剪掉全球最长指甲。","url":"https://m.weibo.cn/search?containerid=100103type%3D1%26t%3D10%26q%3D%23%E5%A5%B3%E5%AD%90%E5%89%AA%E6%8E%89%E5%85%A8%E7%90%83%E6%9C%80%E9%95%BF%E6%8C%87%E7%94%B2%23&isnewpage=1&extparam=seat%3D1%26filter_type%3Drealtimehot%26dgr%3D0%26cate%3D0%26pos%3D1%26realpos%3D2%26flag%3D0%26c_type%3D31%26display_time%3D1617948744&luicode=10000011&lfid=106003type%3D25%26t%3D3%26disable_hot%3D1%26filter_type%3Drealtimehot","hot":1983062,"ads":false},{"title":"喻言反差音色大揭秘","category":"明星  ","description":"4月10日“喻”你相遇 #荔枝声音节# ！现在进入@荔枝APP 参与声鉴锦鲤活动，#晒出你的音色# ，揭秘@THE9-喻言 的反差音色，还有机会赢取连麦福利噢～\n\n关注@THE9-喻言 电台，持续解锁“yu”你有关的独家留言！","url":"https://m.weibo.cn/search?containerid=100103type%3D1%26t%3D10%26q%3D%23%E5%96%BB%E8%A8%80%E5%8F%8D%E5%B7%AE%E9%9F%B3%E8%89%B2%E5%A4%A7%E6%8F%AD%E7%A7%98%23&isnewpage=1&extparam=seat%3D1%26filter_type%3Drealtimehot%26dgr%3D0%26cate%3D0%26topic_ad%3D1%26pos%3D2%26c_type%3D31%26adid%3D116930%26display_time%3D1617948744&luicode=10000011&lfid=106003type%3D25%26t%3D3%26disable_hot%3D1%26filter_type%3Drealtimehot","hot":1939469,"ads":true},{"title":"刘涛喊易烊千玺女婿","category":"明星-内地  ","description":"刘涛入职新浪娱乐，在猜人游戏环节，看到易烊千玺的照片后大喊一声“我女婿”！","url":"https://m.weibo.cn/search?containerid=100103type%3D1%26t%3D10%26q%3D%23%E5%88%98%E6%B6%9B%E5%96%8A%E6%98%93%E7%83%8A%E5%8D%83%E7%8E%BA%E5%A5%B3%E5%A9%BF%23&isnewpage=1&extparam=seat%3D1%26filter_type%3Drealtimehot%26dgr%3D0%26cate%3D0%26pos%3D3%26realpos%3D3%26flag%3D1%26c_type%3D31%26display_time%3D1617948744&luicode=10000011&lfid=106003type%3D25%26t%3D3%26disable_hot%3D1%26filter_type%3Drealtimehot","hot":1903801,"ads":false},{"title":"向往的生活第五季定档","category":"综艺-内地综艺  ","description":"向往的生活定档了！4月23日22:00首播（划重点）！","url":"https://m.weibo.cn/search?containerid=100103type%3D1%26t%3D10%26q%3D%23%E5%90%91%E5%BE%80%E7%9A%84%E7%94%9F%E6%B4%BB%E7%AC%AC%E4%BA%94%E5%AD%A3%E5%AE%9A%E6%A1%A3%23&isnewpage=1&extparam=seat%3D1%26filter_type%3Drealtimehot%26dgr%3D0%26cate%3D0%26pos%3D4%26realpos%3D4%26flag%3D16%26c_type%3D31%26display_time%3D1617948744&luicode=10000011&lfid=106003type%3D25%26t%3D3%26disable_hot%3D1%26filter_type%3Drealtimehot","hot":1045239,"ads":false},{"title":"肖战工作室获得行政许可","category":"财经  ","description":"企查查APP显示，厦门仲夏之月文化传媒有限公司（肖战工作室）于4月1日获得广播电视节目制作经营许可证，许可机关为福建省广播电视局，有效期至2023年3月31日。","url":"https://m.weibo.cn/search?containerid=100103type%3D1%26t%3D10%26q%3D%23%E8%82%96%E6%88%98%E5%B7%A5%E4%BD%9C%E5%AE%A4%E8%8E%B7%E5%BE%97%E8%A1%8C%E6%94%BF%E8%AE%B8%E5%8F%AF%23&isnewpage=1&extparam=seat%3D1%26filter_type%3Drealtimehot%26dgr%3D0%26cate%3D0%26pos%3D5%26realpos%3D5%26flag%3D16%26c_type%3D31%26display_time%3D1617948744&luicode=10000011&lfid=106003type%3D25%26t%3D3%26disable_hot%3D1%26filter_type%3Drealtimehot","hot":960368,"ads":false},{"title":"哈里斯承认美国为石油发动战争","category":"社会  ","description":"美国《国会山》日报7日发布了一段美国副总统哈里斯的讲话，哈里斯称自己参加过很多美国外交政策会议，她说，过去很多年，几代人都在为石油而战，而在不久的将来将会为水资源而战。","url":"https://m.weibo.cn/search?containerid=100103type%3D1%26t%3D10%26q%3D%23%E5%93%88%E9%87%8C%E6%96%AF%E6%89%BF%E8%AE%A4%E7%BE%8E%E5%9B%BD%E4%B8%BA%E7%9F%B3%E6%B2%B9%E5%8F%91%E5%8A%A8%E6%88%98%E4%BA%89%23&isnewpage=1&extparam=seat%3D1%26filter_type%3Drealtimehot%26dgr%3D0%26cate%3D0%26pos%3D6%26realpos%3D6%26flag%3D1%26c_type%3D31%26display_time%3D1617948744&luicode=10000011&lfid=106003type%3D25%26t%3D3%26disable_hot%3D1%26filter_type%3Drealtimehot","hot":846124,"ads":false},{"title":"手机号66666被拍卖32万替友还债","category":"社会  ","description":"4月4日，阿里拍卖上，黑龙江佳木斯的一尾号66666手机号经过45轮竞拍，最终以32万多成交。记者从平台处了解到，手机号持有者为朋友担保，朋友中途跑路。作为担保人，为了偿还债务，号主只能选择将手机号拍卖，替友还债。","url":"https://m.weibo.cn/search?containerid=100103type%3D1%26t%3D10%26q%3D%23%E6%89%8B%E6%9C%BA%E5%8F%B766666%E8%A2%AB%E6%8B%8D%E5%8D%9632%E4%B8%87%E6%9B%BF%E5%8F%8B%E8%BF%98%E5%80%BA%23&isnewpage=1&extparam=seat%3D1%26filter_type%3Drealtimehot%26dgr%3D0%26cate%3D0%26pos%3D7%26realpos%3D7%26flag%3D0%26c_type%3D31%26display_time%3D1617948744&luicode=10000011&lfid=106003type%3D25%26t%3D3%26disable_hot%3D1%26filter_type%3Drealtimehot","hot":767168,"ads":false},{"title":"幼儿园不得设学前班","category":"社会  ","description":"日前，教育部印发《关于大力推进幼儿园与小学科学衔接的指导意见》，文件强调，小学严格执行免试就近入学","url":"https://m.weibo.cn/search?containerid=100103type%3D1%26t%3D10%26q%3D%23%E5%B9%BC%E5%84%BF%E5%9B%AD%E4%B8%8D%E5%BE%97%E8%AE%BE%E5%AD%A6%E5%89%8D%E7%8F%AD%23&isnewpage=1&extparam=seat%3D1%26filter_type%3Drealtimehot%26dgr%3D0%26cate%3D0%26pos%3D8%26realpos%3D8%26flag%3D1%26c_type%3D31%26display_time%3D1617948744&luicode=10000011&lfid=106003type%3D25%26t%3D3%26disable_hot%3D1%26filter_type%3Drealtimehot","hot":688811,"ads":false},{"title":"顺丰跌停","category":"财经  ","description":"4月8日晚间，顺丰控股发布公告称，一季度净亏损9亿至11亿元，而上年同期盈利9.07亿。 ​","url":"https://m.weibo.cn/search?containerid=100103type%3D1%26t%3D10%26q%3D%E9%A1%BA%E4%B8%B0%E8%B7%8C%E5%81%9C&isnewpage=1&extparam=seat%3D1%26filter_type%3Drealtimehot%26dgr%3D0%26cate%3D0%26pos%3D9%26realpos%3D9%26flag%3D0%26c_type%3D31%26display_time%3D1617948744&luicode=10000011&lfid=106003type%3D25%26t%3D3%26disable_hot%3D1%26filter_type%3Drealtimehot","hot":532728,"ads":false},{"title":"林依晨送公公上班图","url":"https://m.weibo.cn/search?containerid=100103type%3D1%26t%3D10%26q%3D%23%E6%9E%97%E4%BE%9D%E6%99%A8%E9%80%81%E5%85%AC%E5%85%AC%E4%B8%8A%E7%8F%AD%E5%9B%BE%23&isnewpage=1&extparam=seat%3D1%26filter_type%3Drealtimehot%26dgr%3D0%26cate%3D0%26pos%3D10%26realpos%3D10%26flag%3D16%26c_type%3D31%26display_time%3D1617948744&luicode=10000011&lfid=106003type%3D25%26t%3D3%26disable_hot%3D1%26filter_type%3Drealtimehot","hot":519675,"ads":false},{"title":"那英组日不落空中瑜伽","url":"https://m.weibo.cn/search?containerid=100103type%3D1%26t%3D10%26q%3D%E9%82%A3%E8%8B%B1%E7%BB%84%E6%97%A5%E4%B8%8D%E8%90%BD%E7%A9%BA%E4%B8%AD%E7%91%9C%E4%BC%BD&isnewpage=1&extparam=seat%3D1%26filter_type%3Drealtimehot%26dgr%3D0%26cate%3D0%26pos%3D11%26realpos%3D11%26flag%3D1%26c_type%3D31%26display_time%3D1617948744&luicode=10000011&lfid=106003type%3D25%26t%3D3%26disable_hot%3D1%26filter_type%3Drealtimehot","hot":504281,"ads":false},{"title":"刘诗诗短发","category":"明星-内地  ","description":"刘诗诗《时尚COSMO》5月刊封面出炉，短发造型英气干练，你喜欢吗？","url":"https://m.weibo.cn/search?containerid=100103type%3D1%26t%3D10%26q%3D%E5%88%98%E8%AF%97%E8%AF%97%E7%9F%AD%E5%8F%91&isnewpage=1&extparam=seat%3D1%26filter_type%3Drealtimehot%26dgr%3D0%26cate%3D0%26pos%3D12%26realpos%3D12%26flag%3D0%26c_type%3D31%26display_time%3D1617948744&luicode=10000011&lfid=106003type%3D25%26t%3D3%26disable_hot%3D1%26filter_type%3Drealtimehot","hot":490822,"ads":false},{"title":"小学严格执行免试就近入学","category":"社会  ","description":"日前，教育部印发《关于大力推进幼儿园与小学科学衔接的指导意见》，文件强调，小学严格执行免试就近入学","url":"https://m.weibo.cn/search?containerid=100103type%3D1%26t%3D10%26q%3D%23%E5%B0%8F%E5%AD%A6%E4%B8%A5%E6%A0%BC%E6%89%A7%E8%A1%8C%E5%85%8D%E8%AF%95%E5%B0%B1%E8%BF%91%E5%85%A5%E5%AD%A6%23&isnewpage=1&extparam=seat%3D1%26filter_type%3Drealtimehot%26dgr%3D0%26cate%3D0%26pos%3D13%26realpos%3D13%26flag%3D0%26c_type%3D31%26display_time%3D1617948744&luicode=10000011&lfid=106003type%3D25%26t%3D3%26disable_hot%3D1%26filter_type%3Drealtimehot","hot":479381,"ads":false},{"title":"马斯克公布猴子用意念打游戏视频","category":"互联网  ","description":"马斯克旗下脑机接口公司周四公布了一段名为“帕格”(Pager)的9岁猕猴玩乒乓球电子游戏的视频。帕格的脑中被植入了Neuralink设备。视频中，帕格利用它的脑部活动学习控制一台电脑，以“品尝到通过金属吸管提供的美味香蕉奶昔”。","url":"https://m.weibo.cn/search?containerid=100103type%3D1%26t%3D10%26q%3D%E9%A9%AC%E6%96%AF%E5%85%8B%E5%85%AC%E5%B8%83%E7%8C%B4%E5%AD%90%E7%94%A8%E6%84%8F%E5%BF%B5%E6%89%93%E6%B8%B8%E6%88%8F%E8%A7%86%E9%A2%91&isnewpage=1&extparam=seat%3D1%26filter_type%3Drealtimehot%26dgr%3D0%26cate%3D0%26pos%3D14%26realpos%3D14%26flag%3D1%26c_type%3D31%26display_time%3D1617948744&luicode=10000011&lfid=106003type%3D25%26t%3D3%26disable_hot%3D1%26filter_type%3Drealtimehot","hot":466407,"ads":false},{"title":"乘风破浪的姐姐总决赛","category":"综艺-内地综艺  ","description":"《乘风破浪的姐姐2》总决赛高能继续，黄子韬惊喜助阵。那英、周笔畅 两组终极PK，姐姐们都拼了！谁能成功成团？让我们拭目以待！","url":"https://m.weibo.cn/search?containerid=100103type%3D1%26t%3D10%26q%3D%E4%B9%98%E9%A3%8E%E7%A0%B4%E6%B5%AA%E7%9A%84%E5%A7%90%E5%A7%90%E6%80%BB%E5%86%B3%E8%B5%9B&isnewpage=1&extparam=seat%3D1%26filter_type%3Drealtimehot%26dgr%3D0%26cate%3D0%26pos%3D15%26realpos%3D15%26flag%3D0%26c_type%3D31%26display_time%3D1617948744&luicode=10000011&lfid=106003type%3D25%26t%3D3%26disable_hot%3D1%26filter_type%3Drealtimehot","hot":443619,"ads":false},{"title":"女毕业生实名举报老师性骚扰","category":"社会  ","description":"女毕业生实名举报高中数学老师性骚扰，警方介入调查。","url":"https://m.weibo.cn/search?containerid=100103type%3D1%26t%3D10%26q%3D%23%E5%A5%B3%E6%AF%95%E4%B8%9A%E7%94%9F%E5%AE%9E%E5%90%8D%E4%B8%BE%E6%8A%A5%E8%80%81%E5%B8%88%E6%80%A7%E9%AA%9A%E6%89%B0%23&isnewpage=1&extparam=seat%3D1%26filter_type%3Drealtimehot%26dgr%3D0%26cate%3D0%26pos%3D16%26realpos%3D16%26flag%3D0%26c_type%3D31%26display_time%3D1617948744&luicode=10000011&lfid=106003type%3D25%26t%3D3%26disable_hot%3D1%26filter_type%3Drealtimehot","hot":443239,"ads":false},{"title":"董思成 天官赐福","url":"https://m.weibo.cn/search?containerid=100103type%3D1%26t%3D10%26q%3D%E8%91%A3%E6%80%9D%E6%88%90+%E5%A4%A9%E5%AE%98%E8%B5%90%E7%A6%8F&isnewpage=1&extparam=seat%3D1%26filter_type%3Drealtimehot%26dgr%3D0%26cate%3D0%26pos%3D17%26realpos%3D17%26flag%3D0%26c_type%3D31%26display_time%3D1617948744&luicode=10000011&lfid=106003type%3D25%26t%3D3%26disable_hot%3D1%26filter_type%3Drealtimehot","hot":434051,"ads":false},{"title":"向往的生活家庭氛围感海报","category":"综艺-内地综艺  ","description":"O姐还要继续努力啊！多跟H练习一下表情管理～4月23日起每周五晚22:00，安排～","url":"https://m.weibo.cn/search?containerid=100103type%3D1%26t%3D10%26q%3D%23%E5%90%91%E5%BE%80%E7%9A%84%E7%94%9F%E6%B4%BB%E5%AE%B6%E5%BA%AD%E6%B0%9B%E5%9B%B4%E6%84%9F%E6%B5%B7%E6%8A%A5%23&isnewpage=1&extparam=seat%3D1%26filter_type%3Drealtimehot%26dgr%3D0%26cate%3D0%26pos%3D18%26realpos%3D18%26flag%3D1%26c_type%3D31%26display_time%3D1617948744&luicode=10000011&lfid=106003type%3D25%26t%3D3%26disable_hot%3D1%26filter_type%3Drealtimehot","hot":425425,"ads":false},{"title":"花70万买画女孩被指在娃圈做代理","category":"社会  ","description":"4月8日，13岁女孩芙芙花70万约稿买画后，又被曝出开微店当代理商卖娃娃。","url":"https://m.weibo.cn/search?containerid=100103type%3D1%26t%3D10%26q%3D%E8%8A%B170%E4%B8%87%E4%B9%B0%E7%94%BB%E5%A5%B3%E5%AD%A9%E8%A2%AB%E6%8C%87%E5%9C%A8%E5%A8%83%E5%9C%88%E5%81%9A%E4%BB%A3%E7%90%86&isnewpage=1&extparam=seat%3D1%26filter_type%3Drealtimehot%26dgr%3D0%26cate%3D0%26pos%3D19%26realpos%3D19%26flag%3D0%26c_type%3D31%26display_time%3D1617948744&luicode=10000011&lfid=106003type%3D25%26t%3D3%26disable_hot%3D1%26filter_type%3Drealtimehot","hot":412882,"ads":false},{"title":"张艺兴向往5常驻","category":"综艺  ","description":"《向往的生活》第五季定档4月23日，张艺兴作为常驻嘉宾加盟。","url":"https://m.weibo.cn/search?containerid=100103type%3D1%26t%3D10%26q%3D%23%E5%BC%A0%E8%89%BA%E5%85%B4%E5%90%91%E5%BE%805%E5%B8%B8%E9%A9%BB%23&isnewpage=1&extparam=seat%3D1%26filter_type%3Drealtimehot%26dgr%3D0%26cate%3D0%26pos%3D20%26realpos%3D20%26flag%3D0%26c_type%3D31%26display_time%3D1617948744&luicode=10000011&lfid=106003type%3D25%26t%3D3%26disable_hot%3D1%26filter_type%3Drealtimehot","hot":410204,"ads":false},{"title":"刘涛扫楼","category":"明星-内地  ","description":"星同事刘涛入职新浪娱乐啦！给男小编化妆，喊易烊千玺女婿，全程惊喜多多~","url":"https://m.weibo.cn/search?containerid=100103type%3D1%26t%3D10%26q%3D%23%E5%88%98%E6%B6%9B%E6%89%AB%E6%A5%BC%23&isnewpage=1&extparam=seat%3D1%26filter_type%3Drealtimehot%26dgr%3D0%26cate%3D0%26pos%3D21%26realpos%3D21%26flag%3D1%26c_type%3D31%26display_time%3D1617948744&luicode=10000011&lfid=106003type%3D25%26t%3D3%26disable_hot%3D1%26filter_type%3Drealtimehot","hot":397278,"ads":false},{"title":"择君记官宣","category":"电视剧  ","description":"由知名网络小说作家电线 原著小说《两只前夫一台戏》改编，企鹅影视、深蓝影业联合出品，张雪迎、邢昭林 、王以纶领衔主演的古装甜虐剧网剧《择君记》。","url":"https://m.weibo.cn/search?containerid=100103type%3D1%26t%3D10%26q%3D%23%E6%8B%A9%E5%90%9B%E8%AE%B0%E5%AE%98%E5%AE%A3%23&isnewpage=1&extparam=seat%3D1%26filter_type%3Drealtimehot%26dgr%3D0%26cate%3D0%26pos%3D22%26realpos%3D22%26flag%3D1%26c_type%3D31%26display_time%3D1617948744&luicode=10000011&lfid=106003type%3D25%26t%3D3%26disable_hot%3D1%26filter_type%3Drealtimehot","hot":386237,"ads":false},{"title":"幼儿连续用电子产品不宜超过15分钟","category":"社会  ","description":"日前，教育部发布《关于大力推进幼儿园与小学科学衔接的指导意见》","url":"https://m.weibo.cn/search?containerid=100103type%3D1%26t%3D10%26q%3D%23%E5%B9%BC%E5%84%BF%E8%BF%9E%E7%BB%AD%E7%94%A8%E7%94%B5%E5%AD%90%E4%BA%A7%E5%93%81%E4%B8%8D%E5%AE%9C%E8%B6%85%E8%BF%8715%E5%88%86%E9%92%9F%23&isnewpage=1&extparam=seat%3D1%26filter_type%3Drealtimehot%26dgr%3D0%26cate%3D0%26pos%3D23%26realpos%3D23%26flag%3D1%26c_type%3D31%26display_time%3D1617948744&luicode=10000011&lfid=106003type%3D25%26t%3D3%26disable_hot%3D1%26filter_type%3Drealtimehot","hot":369087,"ads":false},{"title":"山河令花絮","category":"电视剧-国产剧  ","description":"#山河令花絮# 温客行周子舒太好了，山河令花絮多来点～","url":"https://m.weibo.cn/search?containerid=100103type%3D1%26t%3D10%26q%3D%E5%B1%B1%E6%B2%B3%E4%BB%A4%E8%8A%B1%E7%B5%AE&isnewpage=1&extparam=seat%3D1%26filter_type%3Drealtimehot%26dgr%3D0%26cate%3D0%26pos%3D24%26realpos%3D24%26flag%3D1%26c_type%3D31%26display_time%3D1617948744&luicode=10000011&lfid=106003type%3D25%26t%3D3%26disable_hot%3D1%26filter_type%3Drealtimehot","hot":352949,"ads":false},{"title":"龚俊白发造型","category":"明星  ","description":"龚俊最新白发造型曝光，啊啊啊啊啊啊啊啊好绝啊啊啊！","url":"https://m.weibo.cn/search?containerid=100103type%3D1%26t%3D10%26q%3D%E9%BE%9A%E4%BF%8A%E7%99%BD%E5%8F%91%E9%80%A0%E5%9E%8B&isnewpage=1&extparam=seat%3D1%26filter_type%3Drealtimehot%26dgr%3D0%26cate%3D0%26pos%3D25%26realpos%3D25%26flag%3D0%26c_type%3D31%26display_time%3D1617948744&luicode=10000011&lfid=106003type%3D25%26t%3D3%26disable_hot%3D1%26filter_type%3Drealtimehot","hot":344901,"ads":false},{"title":"郑乃馨方回应与李振宁恋情","category":"明星-内地  ","description":"哇唧唧哇回复郑乃馨后援会，表示：“在当下敏感的舆论环境中，其他任何捕风捉影的事情都不及艺人的舞台和出圈机会重要。” ​","url":"https://m.weibo.cn/search?containerid=100103type%3D1%26t%3D10%26q%3D%23%E9%83%91%E4%B9%83%E9%A6%A8%E6%96%B9%E5%9B%9E%E5%BA%94%E4%B8%8E%E6%9D%8E%E6%8C%AF%E5%AE%81%E6%81%8B%E6%83%85%23&isnewpage=1&extparam=seat%3D1%26filter_type%3Drealtimehot%26dgr%3D0%26cate%3D0%26pos%3D26%26realpos%3D26%26flag%3D0%26c_type%3D31%26display_time%3D1617948744&luicode=10000011&lfid=106003type%3D25%26t%3D3%26disable_hot%3D1%26filter_type%3Drealtimehot","hot":316605,"ads":false},{"title":"韩媒吐槽中国球迷加油声太大","category":"体育  ","description":"奥预赛韩国女足不敌中国，赛后韩国媒体不服输，吐槽现场助威的中国球迷声音过大","url":"https://m.weibo.cn/search?containerid=100103type%3D1%26t%3D10%26q%3D%23%E9%9F%A9%E5%AA%92%E5%90%90%E6%A7%BD%E4%B8%AD%E5%9B%BD%E7%90%83%E8%BF%B7%E5%8A%A0%E6%B2%B9%E5%A3%B0%E5%A4%AA%E5%A4%A7%23&isnewpage=1&extparam=seat%3D1%26filter_type%3Drealtimehot%26dgr%3D0%26cate%3D0%26pos%3D27%26realpos%3D27%26flag%3D0%26c_type%3D31%26display_time%3D1617948744&luicode=10000011&lfid=106003type%3D25%26t%3D3%26disable_hot%3D1%26filter_type%3Drealtimehot","hot":283780,"ads":false},{"title":"人大回应多名考生复试0分","category":"社会  ","description":"4月7日，中国人民大学发布了法学类研究生的拟录取名单，34名考生复试成绩0分。对此，中国人民大学法学院一工作人员表示，确有0分考生存在的情况，但并不清楚是否是因“泄题”导致的处罚。","url":"https://m.weibo.cn/search?containerid=100103type%3D1%26t%3D10%26q%3D%23%E4%BA%BA%E5%A4%A7%E5%9B%9E%E5%BA%94%E5%A4%9A%E5%90%8D%E8%80%83%E7%94%9F%E5%A4%8D%E8%AF%950%E5%88%86%23&isnewpage=1&extparam=seat%3D1%26filter_type%3Drealtimehot%26dgr%3D0%26cate%3D0%26pos%3D28%26realpos%3D28%26flag%3D0%26c_type%3D31%26display_time%3D1617948744&luicode=10000011&lfid=106003type%3D25%26t%3D3%26disable_hot%3D1%26filter_type%3Drealtimehot","hot":277151,"ads":false},{"title":"拐卖妇女儿童乞丐哥获刑13年半","category":"社会  ","description":"红星新闻从官方渠道获悉，因犯拐卖妇女、儿童罪，高德飞被法院判处有期徒刑13年6个月。","url":"https://m.weibo.cn/search?containerid=100103type%3D1%26t%3D10%26q%3D%23%E6%8B%90%E5%8D%96%E5%A6%87%E5%A5%B3%E5%84%BF%E7%AB%A5%E4%B9%9E%E4%B8%90%E5%93%A5%E8%8E%B7%E5%88%9113%E5%B9%B4%E5%8D%8A%23&isnewpage=1&extparam=seat%3D1%26filter_type%3Drealtimehot%26dgr%3D0%26cate%3D0%26pos%3D29%26realpos%3D29%26flag%3D1%26c_type%3D31%26display_time%3D1617948744&luicode=10000011&lfid=106003type%3D25%26t%3D3%26disable_hot%3D1%26filter_type%3Drealtimehot","hot":272969,"ads":false},{"title":"新疆网红怼外媒","category":"社会  ","description":"新疆女孩Aytuna最喜欢拍的就是自己生活的日常，有一次她在裁缝店和妈妈买了条裙子，到了外媒口中就成了“强制劳动的缝纫女工”。","url":"https://m.weibo.cn/search?containerid=100103type%3D1%26t%3D10%26q%3D%23%E6%96%B0%E7%96%86%E7%BD%91%E7%BA%A2%E6%80%BC%E5%A4%96%E5%AA%92%23&isnewpage=1&extparam=seat%3D1%26filter_type%3Drealtimehot%26dgr%3D0%26cate%3D0%26pos%3D30%26realpos%3D30%26flag%3D0%26c_type%3D31%26display_time%3D1617948744&luicode=10000011&lfid=106003type%3D25%26t%3D3%26disable_hot%3D1%26filter_type%3Drealtimehot","hot":238781,"ads":false},{"title":"当小学老师也太快乐了","category":"搞笑  ","description":"哈哈当小学老师也太快乐了，你无法想象孩子果然是人类快乐源泉！","url":"https://m.weibo.cn/search?containerid=100103type%3D1%26t%3D10%26q%3D%23%E5%BD%93%E5%B0%8F%E5%AD%A6%E8%80%81%E5%B8%88%E4%B9%9F%E5%A4%AA%E5%BF%AB%E4%B9%90%E4%BA%86%23&isnewpage=1&extparam=seat%3D1%26filter_type%3Drealtimehot%26dgr%3D0%26cate%3D0%26pos%3D31%26realpos%3D31%26flag%3D0%26c_type%3D31%26display_time%3D1617948744&luicode=10000011&lfid=106003type%3D25%26t%3D3%26disable_hot%3D1%26filter_type%3Drealtimehot","hot":235265,"ads":false},{"title":"所谓涉疆数据库是造假库谣言库伪证库","category":"社会  ","description":"新疆维吾尔自治区人民政府新闻发言人，以及新疆政法机关相关负责人，用大量事实和数据驳斥美西方反华势力炮制的所谓涉疆“数据库”，是彻头彻尾的“造假库”“谣言库”“伪证库”。","url":"https://m.weibo.cn/search?containerid=100103type%3D1%26t%3D10%26q%3D%23%E6%89%80%E8%B0%93%E6%B6%89%E7%96%86%E6%95%B0%E6%8D%AE%E5%BA%93%E6%98%AF%E9%80%A0%E5%81%87%E5%BA%93%E8%B0%A3%E8%A8%80%E5%BA%93%E4%BC%AA%E8%AF%81%E5%BA%93%23&isnewpage=1&extparam=seat%3D1%26filter_type%3Drealtimehot%26dgr%3D0%26cate%3D0%26pos%3D32%26realpos%3D32%26flag%3D1%26c_type%3D31%26display_time%3D1617948744&luicode=10000011&lfid=106003type%3D25%26t%3D3%26disable_hot%3D1%26filter_type%3Drealtimehot","hot":223568,"ads":false},{"title":"陕科大与西安工大因地铁站命名起争端","category":"社会  ","description":"西安工业大学和陕西科技大学关于西安地铁14号线站点命名的争议，已蔓延至线下。","url":"https://m.weibo.cn/search?containerid=100103type%3D1%26t%3D10%26q%3D%23%E9%99%95%E7%A7%91%E5%A4%A7%E4%B8%8E%E8%A5%BF%E5%AE%89%E5%B7%A5%E5%A4%A7%E5%9B%A0%E5%9C%B0%E9%93%81%E7%AB%99%E5%91%BD%E5%90%8D%E8%B5%B7%E4%BA%89%E7%AB%AF%23&isnewpage=1&extparam=seat%3D1%26filter_type%3Drealtimehot%26dgr%3D0%26cate%3D0%26pos%3D33%26realpos%3D33%26flag%3D0%26c_type%3D31%26display_time%3D1617948744&luicode=10000011&lfid=106003type%3D25%26t%3D3%26disable_hot%3D1%26filter_type%3Drealtimehot","hot":205457,"ads":false},{"title":"CNN记者摊牌就是要抹黑中国","category":"社会  ","description":"#CNN记者摊牌就是要抹黑中国#，“要让中国在国际舞台上看起来像个坏蛋”","url":"https://m.weibo.cn/search?containerid=100103type%3D1%26t%3D10%26q%3D%23CNN%E8%AE%B0%E8%80%85%E6%91%8A%E7%89%8C%E5%B0%B1%E6%98%AF%E8%A6%81%E6%8A%B9%E9%BB%91%E4%B8%AD%E5%9B%BD%23&isnewpage=1&extparam=seat%3D1%26filter_type%3Drealtimehot%26dgr%3D0%26cate%3D0%26pos%3D34%26realpos%3D34%26flag%3D1%26c_type%3D31%26display_time%3D1617948744&luicode=10000011&lfid=106003type%3D25%26t%3D3%26disable_hot%3D1%26filter_type%3Drealtimehot","hot":204213,"ads":false},{"title":"在清华大学读书有哪些烦恼","category":"搞笑  ","description":"带着话题发微博，说一说你的大学生活都有哪些烦恼吧！转赞评＞5就可以入围，一起来抢热门吧！","url":"https://m.weibo.cn/search?containerid=100103type%3D1%26t%3D10%26q%3D%23%E5%9C%A8%E6%B8%85%E5%8D%8E%E5%A4%A7%E5%AD%A6%E8%AF%BB%E4%B9%A6%E6%9C%89%E5%93%AA%E4%BA%9B%E7%83%A6%E6%81%BC%23&isnewpage=1&extparam=seat%3D1%26filter_type%3Drealtimehot%26dgr%3D0%26cate%3D0%26pos%3D35%26realpos%3D35%26flag%3D0%26c_type%3D31%26display_time%3D1617948744&luicode=10000011&lfid=106003type%3D25%26t%3D3%26disable_hot%3D1%26filter_type%3Drealtimehot","hot":195011,"ads":false},{"title":"日本政府基本决定将福岛核污水排入大海","category":"财经-宏观经济  ","description":"日本政府今日基本决定将福岛第一核电站核污水排入大海。4月13日，日本政府将召开内阁会议，正式决定。此间日本舆论认为，此举势必引起日本渔民以及国际社会的反对。 ​","url":"https://m.weibo.cn/search?containerid=100103type%3D1%26t%3D10%26q%3D%E6%97%A5%E6%9C%AC%E6%94%BF%E5%BA%9C%E5%9F%BA%E6%9C%AC%E5%86%B3%E5%AE%9A%E5%B0%86%E7%A6%8F%E5%B2%9B%E6%A0%B8%E6%B1%A1%E6%B0%B4%E6%8E%92%E5%85%A5%E5%A4%A7%E6%B5%B7&isnewpage=1&extparam=seat%3D1%26filter_type%3Drealtimehot%26dgr%3D0%26cate%3D0%26pos%3D36%26realpos%3D36%26flag%3D1%26c_type%3D31%26display_time%3D1617948744&luicode=10000011&lfid=106003type%3D25%26t%3D3%26disable_hot%3D1%26filter_type%3Drealtimehot","hot":181836,"ads":false},{"title":"小朋友的话有多治愈","category":"搞笑  ","description":"小朋友天真的话真的能够温暖治愈到我们这些已经经历过社会毒打的内心～快来分享一下你被小朋友的语言治愈过的经历呀","url":"https://m.weibo.cn/search?containerid=100103type%3D1%26t%3D10%26q%3D%23%E5%B0%8F%E6%9C%8B%E5%8F%8B%E7%9A%84%E8%AF%9D%E6%9C%89%E5%A4%9A%E6%B2%BB%E6%84%88%23&isnewpage=1&extparam=seat%3D1%26filter_type%3Drealtimehot%26dgr%3D0%26cate%3D0%26pos%3D37%26realpos%3D37%26flag%3D1%26c_type%3D31%26display_time%3D1617948744&luicode=10000011&lfid=106003type%3D25%26t%3D3%26disable_hot%3D1%26filter_type%3Drealtimehot","hot":181656,"ads":false},{"title":"云南发现3个萤火虫新种","category":"社会  ","description":"近日，据中国科学院昆明动物研究所官网，该所进化基因组学与基因起源研究组，在云南发现了3个萤火虫新种：在丽江玉龙发现高山扁萤，在禄劝彝族苗族自治县轿子山附近发现禄劝扁萤，在红河哈尼族彝族自治州元阳县黄茅岭乡发现巨胸扁萤。","url":"https://m.weibo.cn/search?containerid=100103type%3D1%26t%3D10%26q%3D%23%E4%BA%91%E5%8D%97%E5%8F%91%E7%8E%B03%E4%B8%AA%E8%90%A4%E7%81%AB%E8%99%AB%E6%96%B0%E7%A7%8D%23&isnewpage=1&extparam=seat%3D1%26filter_type%3Drealtimehot%26dgr%3D0%26cate%3D0%26pos%3D38%26realpos%3D38%26flag%3D1%26c_type%3D31%26display_time%3D1617948744&luicode=10000011&lfid=106003type%3D25%26t%3D3%26disable_hot%3D1%26filter_type%3Drealtimehot","hot":179412,"ads":false},{"title":"山河令","category":"电视剧  ","description":"本剧讲述了天窗首领周子舒为求自由，不惜以生命为代价退出组织，命不久矣之际遇上一心灭世的鬼谷谷主温客行，两人因卷入江湖纷争相识相知，最终成为彼此救赎的故事。一场阴谋，两个知己，五块宝藏拼图，廿载恩怨，千百年江湖梦。","url":"https://m.weibo.cn/search?containerid=100103type%3D1%26t%3D10%26q%3D%E5%B1%B1%E6%B2%B3%E4%BB%A4&isnewpage=1&extparam=seat%3D1%26filter_type%3Drealtimehot%26dgr%3D0%26cate%3D0%26pos%3D39%26realpos%3D39%26flag%3D0%26c_type%3D31%26display_time%3D1617948744&luicode=10000011&lfid=106003type%3D25%26t%3D3%26disable_hot%3D1%26filter_type%3Drealtimehot","hot":178063,"ads":false},{"title":"创造营智族GQ男孩与偶像大片","category":"综艺  ","description":"#创造营#2021智族GQ男孩与偶像大片上线！快来看！","url":"https://m.weibo.cn/search?containerid=100103type%3D1%26t%3D10%26q%3D%23%E5%88%9B%E9%80%A0%E8%90%A5%E6%99%BA%E6%97%8FGQ%E7%94%B7%E5%AD%A9%E4%B8%8E%E5%81%B6%E5%83%8F%E5%A4%A7%E7%89%87%23&isnewpage=1&extparam=seat%3D1%26filter_type%3Drealtimehot%26dgr%3D0%26cate%3D0%26pos%3D40%26realpos%3D40%26flag%3D1%26c_type%3D31%26display_time%3D1617948744&luicode=10000011&lfid=106003type%3D25%26t%3D3%26disable_hot%3D1%26filter_type%3Drealtimehot","hot":176026,"ads":false},{"title":"作为女性所遭受的语言暴力","category":"搞笑  ","description":"生活中，作为一名女性，你遭受过哪些不可思议的语言暴力？","url":"https://m.weibo.cn/search?containerid=100103type%3D1%26t%3D10%26q%3D%23%E4%BD%9C%E4%B8%BA%E5%A5%B3%E6%80%A7%E6%89%80%E9%81%AD%E5%8F%97%E7%9A%84%E8%AF%AD%E8%A8%80%E6%9A%B4%E5%8A%9B%23&isnewpage=1&extparam=seat%3D1%26filter_type%3Drealtimehot%26dgr%3D0%26cate%3D0%26pos%3D41%26realpos%3D41%26flag%3D1%26c_type%3D31%26display_time%3D1617948744&luicode=10000011&lfid=106003type%3D25%26t%3D3%26disable_hot%3D1%26filter_type%3Drealtimehot","hot":175132,"ads":false},{"title":"长歌行","category":"电视剧  ","description":"电视剧  ","url":"https://m.weibo.cn/search?containerid=100103type%3D1%26t%3D10%26q%3D%E9%95%BF%E6%AD%8C%E8%A1%8C&isnewpage=1&extparam=seat%3D1%26filter_type%3Drealtimehot%26dgr%3D0%26cate%3D0%26pos%3D42%26realpos%3D42%26flag%3D1%26c_type%3D31%26display_time%3D1617948744&luicode=10000011&lfid=106003type%3D25%26t%3D3%26disable_hot%3D1%26filter_type%3Drealtimehot","hot":173264,"ads":false},{"title":"隋文静韩聪牵手十四周年","category":"体育  ","description":"@Guile隋文静 和@Allen韩聪 牵手14年，十四年光阴的陪伴，穿越伤痛和失意，他们已经成长为冰面上最闪耀的光！","url":"https://m.weibo.cn/search?containerid=100103type%3D1%26t%3D10%26q%3D%23%E9%9A%8B%E6%96%87%E9%9D%99%E9%9F%A9%E8%81%AA%E7%89%B5%E6%89%8B%E5%8D%81%E5%9B%9B%E5%91%A8%E5%B9%B4%23&isnewpage=1&extparam=seat%3D1%26filter_type%3Drealtimehot%26dgr%3D0%26cate%3D0%26pos%3D43%26realpos%3D43%26flag%3D1%26c_type%3D31%26display_time%3D1617948744&luicode=10000011&lfid=106003type%3D25%26t%3D3%26disable_hot%3D1%26filter_type%3Drealtimehot","hot":171824,"ads":false},{"title":"我的姐姐未曝光片段","category":"电影-华语电影  ","description":"电影《我的姐姐》未曝光片段，正片中葬礼结束，家族争吵之后，姐姐弟弟、舅舅姑妈，一起送离去的人最后一程。","url":"https://m.weibo.cn/search?containerid=100103type%3D1%26t%3D10%26q%3D%23%E6%88%91%E7%9A%84%E5%A7%90%E5%A7%90%E6%9C%AA%E6%9B%9D%E5%85%89%E7%89%87%E6%AE%B5%23&isnewpage=1&extparam=seat%3D1%26filter_type%3Drealtimehot%26dgr%3D0%26cate%3D0%26pos%3D44%26realpos%3D44%26flag%3D0%26c_type%3D31%26display_time%3D1617948744&luicode=10000011&lfid=106003type%3D25%26t%3D3%26disable_hot%3D1%26filter_type%3Drealtimehot","hot":171124,"ads":false},{"title":"周笔畅组唱我哭了","category":"综艺-内地综艺  ","description":"《乘风破浪的姐姐》周笔畅组献唱《我》，动情处姐姐们眼含泪光。","url":"https://m.weibo.cn/search?containerid=100103type%3D1%26t%3D10%26q%3D%23%E5%91%A8%E7%AC%94%E7%95%85%E7%BB%84%E5%94%B1%E6%88%91%E5%93%AD%E4%BA%86%23&isnewpage=1&extparam=seat%3D1%26filter_type%3Drealtimehot%26dgr%3D0%26cate%3D0%26pos%3D45%26realpos%3D45%26flag%3D1%26c_type%3D31%26display_time%3D1617948744&luicode=10000011&lfid=106003type%3D25%26t%3D3%26disable_hot%3D1%26filter_type%3Drealtimehot","hot":168305,"ads":false},{"title":"一年级课程主要采取游戏化等方式","category":"社会  ","description":"日前，教育部发布《关于大力推进幼儿园与小学科学衔接的指导意见》。","url":"https://m.weibo.cn/search?containerid=100103type%3D1%26t%3D10%26q%3D%23%E4%B8%80%E5%B9%B4%E7%BA%A7%E8%AF%BE%E7%A8%8B%E4%B8%BB%E8%A6%81%E9%87%87%E5%8F%96%E6%B8%B8%E6%88%8F%E5%8C%96%E7%AD%89%E6%96%B9%E5%BC%8F%23&isnewpage=1&extparam=seat%3D1%26filter_type%3Drealtimehot%26dgr%3D0%26cate%3D0%26pos%3D46%26realpos%3D46%26flag%3D1%26c_type%3D31%26display_time%3D1617948744&luicode=10000011&lfid=106003type%3D25%26t%3D3%26disable_hot%3D1%26filter_type%3Drealtimehot","hot":166513,"ads":false},{"title":"2021年第100天","category":"社会  ","description":"过完今天，就迎来了#2021年第100天#，丢掉遗憾和不快。提升幸福感，多晚都来得及。","url":"https://m.weibo.cn/search?containerid=100103type%3D1%26t%3D10%26q%3D%232021%E5%B9%B4%E7%AC%AC100%E5%A4%A9%23&isnewpage=1&extparam=seat%3D1%26filter_type%3Drealtimehot%26dgr%3D0%26cate%3D0%26pos%3D47%26realpos%3D47%26flag%3D0%26c_type%3D31%26display_time%3D1617948744&luicode=10000011&lfid=106003type%3D25%26t%3D3%26disable_hot%3D1%26filter_type%3Drealtimehot","hot":161409,"ads":false},{"title":"顺丰控股一季度预亏约10亿元","category":"财经  ","description":"4月8日晚，顺丰控股发布2021年第一季度业绩预告，预计一季度亏损9亿至11亿元。公司2020年同期盈利9.07亿元。","url":"https://m.weibo.cn/search?containerid=100103type%3D1%26t%3D10%26q%3D%23%E9%A1%BA%E4%B8%B0%E6%8E%A7%E8%82%A1%E4%B8%80%E5%AD%A3%E5%BA%A6%E9%A2%84%E4%BA%8F%E7%BA%A610%E4%BA%BF%E5%85%83%23&isnewpage=1&extparam=seat%3D1%26filter_type%3Drealtimehot%26dgr%3D0%26cate%3D0%26pos%3D48%26realpos%3D48%26flag%3D1%26c_type%3D31%26display_time%3D1617948744&luicode=10000011&lfid=106003type%3D25%26t%3D3%26disable_hot%3D1%26filter_type%3Drealtimehot","hot":145855,"ads":false},{"title":"景甜张彬彬同款跑步姿势","category":"明星-内地  ","description":"明星-内地  ","url":"https://m.weibo.cn/search?containerid=100103type%3D1%26t%3D10%26q%3D%23%E6%99%AF%E7%94%9C%E5%BC%A0%E5%BD%AC%E5%BD%AC%E5%90%8C%E6%AC%BE%E8%B7%91%E6%AD%A5%E5%A7%BF%E5%8A%BF%23&isnewpage=1&extparam=seat%3D1%26filter_type%3Drealtimehot%26dgr%3D0%26cate%3D0%26pos%3D49%26realpos%3D49%26flag%3D0%26c_type%3D31%26display_time%3D1617948744&luicode=10000011&lfid=106003type%3D25%26t%3D3%26disable_hot%3D1%26filter_type%3Drealtimehot","hot":145298,"ads":false}]