[{"title":"27省份上半年GDP数据出炉","category":"社会  ","description":"截至7月26日，除了浙江、河北、西藏、新疆外，其余27个省份已经公布上半年经济成绩单。","url":"https://m.weibo.cn/search?containerid=100103type%3D1%26t%3D10%26q%3D%2327%E7%9C%81%E4%BB%BD%E4%B8%8A%E5%8D%8A%E5%B9%B4GDP%E6%95%B0%E6%8D%AE%E5%87%BA%E7%82%89%23&isnewpage=1&extparam=seat%3D1%26pos%3D0%26dgr%3D0%26c_type%3D51%26filter_type%3Drealtimehot%26cate%3D10103%26display_time%3D1627448769%26pre_seqid%3D1627448769095023476113&luicode=10000011&lfid=106003type%3D25%26t%3D3%26disable_hot%3D1%26filter_type%3Drealtimehot","ads":false},{"title":"张继科发与水谷隼对战视频","category":"体育  ","description":"张继科发了以前自己与水谷隼对战的视频为国乒队加油 ​​​！","url":"https://m.weibo.cn/search?containerid=100103type%3D1%26t%3D10%26q%3D%23%E5%BC%A0%E7%BB%A7%E7%A7%91%E5%8F%91%E4%B8%8E%E6%B0%B4%E8%B0%B7%E9%9A%BC%E5%AF%B9%E6%88%98%E8%A7%86%E9%A2%91%23&isnewpage=1&extparam=seat%3D1%26filter_type%3Drealtimehot%26dgr%3D0%26cate%3D0%26pos%3D0%26realpos%3D1%26flag%3D4%26c_type%3D31%26display_time%3D1627448769%26pre_seqid%3D1627448769095023476113&luicode=10000011&lfid=106003type%3D25%26t%3D3%26disable_hot%3D1%26filter_type%3Drealtimehot","hot":10952031,"ads":false},{"title":"唐山大地震45周年","category":"社会  ","description":"1976年7月28日3时42分，是一串刻在脑海里、足以铭记一生的数字。缅怀逝者，致敬重生！","url":"https://m.weibo.cn/search?containerid=100103type%3D1%26t%3D10%26q%3D%23%E5%94%90%E5%B1%B1%E5%A4%A7%E5%9C%B0%E9%9C%8745%E5%91%A8%E5%B9%B4%23&isnewpage=1&extparam=seat%3D1%26filter_type%3Drealtimehot%26dgr%3D0%26cate%3D0%26pos%3D1%26realpos%3D2%26flag%3D16%26c_type%3D31%26display_time%3D1627448769%26pre_seqid%3D1627448769095023476113&luicode=10000011&lfid=106003type%3D25%26t%3D3%26disable_hot%3D1%26filter_type%3Drealtimehot","hot":4044105,"ads":false},{"title":"陈梦是黄晓明表妹","category":"明星  ","description":"我不会是最后一个知道的吧，国家乒乓球队队员陈梦原来是黄晓明表妹！","url":"https://m.weibo.cn/search?containerid=100103type%3D1%26t%3D10%26q%3D%23%E9%99%88%E6%A2%A6%E6%98%AF%E9%BB%84%E6%99%93%E6%98%8E%E8%A1%A8%E5%A6%B9%23&isnewpage=1&extparam=seat%3D1%26filter_type%3Drealtimehot%26dgr%3D0%26cate%3D0%26pos%3D2%26realpos%3D3%26flag%3D1%26c_type%3D31%26display_time%3D1627448769%26pre_seqid%3D1627448769095023476113&luicode=10000011&lfid=106003type%3D25%26t%3D3%26disable_hot%3D1%26filter_type%3Drealtimehot","hot":3628406,"ads":false},{"title":"暑假锦鲤这奖品太绝了","category":"教育  ","description":"什么是快乐暑假，学而思网校带你研究！关注@学而思网校 ，转发置顶微博，暑假锦鲤大奖等你来拿！更有学而思写作夏令营，领课抽更多好礼 https://activity.xueersi.com/advance/summerCampLottery/#/","url":"https://m.weibo.cn/search?containerid=100103type%3D1%26t%3D10%26q%3D%23%E6%9A%91%E5%81%87%E9%94%A6%E9%B2%A4%E8%BF%99%E5%A5%96%E5%93%81%E5%A4%AA%E7%BB%9D%E4%BA%86%23&isnewpage=1&extparam=seat%3D1%26filter_type%3Drealtimehot%26dgr%3D0%26cate%3D0%26topic_ad%3D1%26pos%3D3%26c_type%3D31%26adid%3D127868%26display_time%3D1627448769%26pre_seqid%3D1627448769095023476113&luicode=10000011&lfid=106003type%3D25%26t%3D3%26disable_hot%3D1%26filter_type%3Drealtimehot","hot":"","ads":true},{"title":"张雨霏优势太明显了","category":"体育  ","description":"@o张雨霏o 以2:04.89的成绩小组第一晋级决赛，一直保持着较大优势！","url":"https://m.weibo.cn/search?containerid=100103type%3D1%26t%3D10%26q%3D%23%E5%BC%A0%E9%9B%A8%E9%9C%8F%E4%BC%98%E5%8A%BF%E5%A4%AA%E6%98%8E%E6%98%BE%E4%BA%86%23&isnewpage=1&extparam=seat%3D1%26filter_type%3Drealtimehot%26dgr%3D0%26cate%3D0%26pos%3D4%26realpos%3D4%26flag%3D1%26c_type%3D31%26display_time%3D1627448769%26pre_seqid%3D1627448769095023476113&luicode=10000011&lfid=106003type%3D25%26t%3D3%26disable_hot%3D1%26filter_type%3Drealtimehot","hot":2672217,"ads":false},{"title":"中国组合赛艇女子四人双桨夺金","category":"社会  ","description":"在刚刚结束的东京奥运会赛艇女子四人双桨决赛上，中国组合陈云霞/张灵/吕扬/崔晓桐夺冠！","url":"https://m.weibo.cn/search?containerid=100103type%3D1%26t%3D10%26q%3D%23%E4%B8%AD%E5%9B%BD%E7%BB%84%E5%90%88%E8%B5%9B%E8%89%87%E5%A5%B3%E5%AD%90%E5%9B%9B%E4%BA%BA%E5%8F%8C%E6%A1%A8%E5%A4%BA%E9%87%91%23&isnewpage=1&extparam=seat%3D1%26filter_type%3Drealtimehot%26dgr%3D0%26cate%3D0%26pos%3D5%26realpos%3D5%26flag%3D16%26c_type%3D31%26display_time%3D1627448769%26pre_seqid%3D1627448769095023476113&luicode=10000011&lfid=106003type%3D25%26t%3D3%26disable_hot%3D1%26filter_type%3Drealtimehot","hot":2358539,"ads":false},{"title":"女子被父亲3次烧毁录取通知书","category":"社会  ","description":"社会  ","url":"https://m.weibo.cn/search?containerid=100103type%3D1%26t%3D10%26q%3D%23%E5%A5%B3%E5%AD%90%E8%A2%AB%E7%88%B6%E4%BA%B23%E6%AC%A1%E7%83%A7%E6%AF%81%E5%BD%95%E5%8F%96%E9%80%9A%E7%9F%A5%E4%B9%A6%23&isnewpage=1&extparam=seat%3D1%26filter_type%3Drealtimehot%26dgr%3D0%26cate%3D0%26pos%3D6%26realpos%3D6%26flag%3D2%26c_type%3D31%26display_time%3D1627448769%26pre_seqid%3D1627448769095023476113&luicode=10000011&lfid=106003type%3D25%26t%3D3%26disable_hot%3D1%26filter_type%3Drealtimehot","hot":2206241,"ads":false},{"title":"樊振东4比0郑荣植晋级4强","category":"社会  ","description":"7月28日，东京奥运会乒乓球男子单打1/4决赛，樊振东4比0郑荣植晋级4强。","url":"https://m.weibo.cn/search?containerid=100103type%3D1%26t%3D10%26q%3D%23%E6%A8%8A%E6%8C%AF%E4%B8%9C4%E6%AF%940%E9%83%91%E8%8D%A3%E6%A4%8D%E6%99%8B%E7%BA%A74%E5%BC%BA%23&isnewpage=1&extparam=seat%3D1%26filter_type%3Drealtimehot%26dgr%3D0%26cate%3D0%26pos%3D7%26realpos%3D7%26flag%3D1%26c_type%3D31%26display_time%3D1627448769%26pre_seqid%3D1627448769095023476113&luicode=10000011&lfid=106003type%3D25%26t%3D3%26disable_hot%3D1%26filter_type%3Drealtimehot","hot":2037258,"ads":false},{"title":"日本男女单打仅剩伊藤美诚","category":"体育  ","description":"日本选手石川佳纯不敌新加坡选手于梦玉，1：4输了，现在日本乒乓球单人比赛只剩下伊藤美诚","url":"https://m.weibo.cn/search?containerid=100103type%3D1%26t%3D10%26q%3D%23%E6%97%A5%E6%9C%AC%E7%94%B7%E5%A5%B3%E5%8D%95%E6%89%93%E4%BB%85%E5%89%A9%E4%BC%8A%E8%97%A4%E7%BE%8E%E8%AF%9A%23&isnewpage=1&extparam=seat%3D1%26filter_type%3Drealtimehot%26dgr%3D0%26cate%3D0%26pos%3D8%26realpos%3D8%26flag%3D2%26c_type%3D31%26display_time%3D1627448769%26pre_seqid%3D1627448769095023476113&luicode=10000011&lfid=106003type%3D25%26t%3D3%26disable_hot%3D1%26filter_type%3Drealtimehot","hot":1957055,"ads":false},{"title":"马琳从椅子上跳起来了","category":"体育  ","description":"@陈梦-乒乓球 逆转赢球的时候，场边的@马琳 高兴的从椅子上跳起来了！","url":"https://m.weibo.cn/search?containerid=100103type%3D1%26t%3D10%26q%3D%23%E9%A9%AC%E7%90%B3%E4%BB%8E%E6%A4%85%E5%AD%90%E4%B8%8A%E8%B7%B3%E8%B5%B7%E6%9D%A5%E4%BA%86%23&isnewpage=1&extparam=seat%3D1%26filter_type%3Drealtimehot%26dgr%3D0%26cate%3D0%26pos%3D9%26realpos%3D9%26flag%3D1%26c_type%3D31%26display_time%3D1627448769%26pre_seqid%3D1627448769095023476113&luicode=10000011&lfid=106003type%3D25%26t%3D3%26disable_hot%3D1%26filter_type%3Drealtimehot","hot":1832825,"ads":false},{"title":"南京发现多起聚集性疫情","category":"社会  ","description":"经流调发现，南京近期新增病例主要集中在机场及周边地区，且报告的病例中已发现多起聚集性疫情。提醒：自觉做到不扎堆不聚集、不串门，坚持做好个人防护。 ​","url":"https://m.weibo.cn/search?containerid=100103type%3D1%26t%3D10%26q%3D%23%E5%8D%97%E4%BA%AC%E5%8F%91%E7%8E%B0%E5%A4%9A%E8%B5%B7%E8%81%9A%E9%9B%86%E6%80%A7%E7%96%AB%E6%83%85%23&isnewpage=1&extparam=seat%3D1%26filter_type%3Drealtimehot%26dgr%3D0%26cate%3D0%26pos%3D10%26realpos%3D10%26flag%3D2%26c_type%3D31%26display_time%3D1627448769%26pre_seqid%3D1627448769095023476113&luicode=10000011&lfid=106003type%3D25%26t%3D3%26disable_hot%3D1%26filter_type%3Drealtimehot","hot":1697380,"ads":false},{"title":"陈梦VS杜凯琹","category":"搞笑  ","description":"你看陈梦和杜凯琹这场战役了嘛？赶紧给中国健儿加油吧！！","url":"https://m.weibo.cn/search?containerid=100103type%3D1%26t%3D10%26q%3D%23%E9%99%88%E6%A2%A6VS%E6%9D%9C%E5%87%AF%E7%90%B9%23&isnewpage=1&extparam=seat%3D1%26filter_type%3Drealtimehot%26dgr%3D0%26cate%3D0%26pos%3D11%26realpos%3D11%26flag%3D2%26c_type%3D31%26display_time%3D1627448769%26pre_seqid%3D1627448769095023476113&luicode=10000011&lfid=106003type%3D25%26t%3D3%26disable_hot%3D1%26filter_type%3Drealtimehot","hot":1659913,"ads":false},{"title":"成都雅颂居","url":"https://m.weibo.cn/search?containerid=100103type%3D1%26t%3D10%26q%3D%23%E6%88%90%E9%83%BD%E9%9B%85%E9%A2%82%E5%B1%85%23&isnewpage=1&extparam=seat%3D1%26filter_type%3Drealtimehot%26dgr%3D0%26cate%3D0%26pos%3D12%26realpos%3D12%26flag%3D2%26c_type%3D31%26display_time%3D1627448769%26pre_seqid%3D1627448769095023476113&luicode=10000011&lfid=106003type%3D25%26t%3D3%26disable_hot%3D1%26filter_type%3Drealtimehot","hot":1528788,"ads":false},{"title":"北京地铁发生雨水倒灌立刻关停电梯","category":"社会  ","description":"今天上午，记者从北京市轨道交通运营管理有限公司获悉，当车站出入口发生雨水倒灌时，立即关停电扶梯、电梯等设施设备；调整闸机方向，引导乘客不要靠近积水区域；通知维修调度中心及排水集团，到车站出入口协助排水；安排安保人员到受影响的出入口值守并张贴通告。","url":"https://m.weibo.cn/search?containerid=100103type%3D1%26t%3D10%26q%3D%23%E5%8C%97%E4%BA%AC%E5%9C%B0%E9%93%81%E5%8F%91%E7%94%9F%E9%9B%A8%E6%B0%B4%E5%80%92%E7%81%8C%E7%AB%8B%E5%88%BB%E5%85%B3%E5%81%9C%E7%94%B5%E6%A2%AF%23&isnewpage=1&extparam=seat%3D1%26filter_type%3Drealtimehot%26dgr%3D0%26cate%3D0%26pos%3D13%26realpos%3D13%26flag%3D1%26c_type%3D31%26display_time%3D1627448769%26pre_seqid%3D1627448769095023476113&luicode=10000011&lfid=106003type%3D25%26t%3D3%26disable_hot%3D1%26filter_type%3Drealtimehot","hot":1420663,"ads":false},{"title":"田亮水花最大的一次入水","category":"搞笑  ","description":"田亮一辈子也没想到，自己水花最大的一次入水，发生在退役之后","url":"https://m.weibo.cn/search?containerid=100103type%3D1%26t%3D10%26q%3D%23%E7%94%B0%E4%BA%AE%E6%B0%B4%E8%8A%B1%E6%9C%80%E5%A4%A7%E7%9A%84%E4%B8%80%E6%AC%A1%E5%85%A5%E6%B0%B4%23&isnewpage=1&extparam=seat%3D1%26filter_type%3Drealtimehot%26dgr%3D0%26cate%3D0%26pos%3D14%26realpos%3D14%26flag%3D2%26c_type%3D31%26display_time%3D1627448769%26pre_seqid%3D1627448769095023476113&luicode=10000011&lfid=106003type%3D25%26t%3D3%26disable_hot%3D1%26filter_type%3Drealtimehot","hot":1417957,"ads":false},{"title":"当花滑比赛放了周杰伦的歌","category":"音乐  ","description":"在花滑比赛上听到周杰伦的歌是什么体验？熟悉的旋律真的听泪目了。","url":"https://m.weibo.cn/search?containerid=100103type%3D1%26t%3D10%26q%3D%23%E5%BD%93%E8%8A%B1%E6%BB%91%E6%AF%94%E8%B5%9B%E6%94%BE%E4%BA%86%E5%91%A8%E6%9D%B0%E4%BC%A6%E7%9A%84%E6%AD%8C%23&isnewpage=1&extparam=seat%3D1%26filter_type%3Drealtimehot%26dgr%3D0%26cate%3D0%26pos%3D15%26realpos%3D15%26flag%3D1%26c_type%3D31%26display_time%3D1627448769%26pre_seqid%3D1627448769095023476113&luicode=10000011&lfid=106003type%3D25%26t%3D3%26disable_hot%3D1%26filter_type%3Drealtimehot","hot":1342634,"ads":false},{"title":"杨倩微博换头像","category":"明星-内地  ","description":"#杨倩微博换头像#杨倩微博换头像了！！这头像过分可爱了！！ ​","url":"https://m.weibo.cn/search?containerid=100103type%3D1%26t%3D10%26q%3D%23%E6%9D%A8%E5%80%A9%E5%BE%AE%E5%8D%9A%E6%8D%A2%E5%A4%B4%E5%83%8F%23&isnewpage=1&extparam=seat%3D1%26filter_type%3Drealtimehot%26dgr%3D0%26cate%3D0%26pos%3D16%26realpos%3D16%26flag%3D2%26c_type%3D31%26display_time%3D1627448769%26pre_seqid%3D1627448769095023476113&luicode=10000011&lfid=106003type%3D25%26t%3D3%26disable_hot%3D1%26filter_type%3Drealtimehot","hot":1308753,"ads":false},{"title":"陈梦逆转晋级四强","category":"体育  ","description":"在刚刚结束的乒乓球女单1/4决赛中，中国选手@陈梦-乒乓球 在0-2落后的情况下连扳4局，以4-2战胜中国香港选手杜凯琹，挺进4强！","url":"https://m.weibo.cn/search?containerid=100103type%3D1%26t%3D10%26q%3D%23%E9%99%88%E6%A2%A6%E9%80%86%E8%BD%AC%E6%99%8B%E7%BA%A7%E5%9B%9B%E5%BC%BA%23&isnewpage=1&extparam=seat%3D1%26filter_type%3Drealtimehot%26dgr%3D0%26cate%3D0%26pos%3D17%26realpos%3D17%26flag%3D1%26c_type%3D31%26display_time%3D1627448769%26pre_seqid%3D1627448769095023476113&luicode=10000011&lfid=106003type%3D25%26t%3D3%26disable_hot%3D1%26filter_type%3Drealtimehot","hot":1305938,"ads":false},{"title":"6岁男孩英语阻止老外景区用无人机","category":"社会  ","description":"7月26日，河南洛阳。6岁男童发现两位外国游客用无人机拍摄佛像，就上前用英文交涉阻止。","url":"https://m.weibo.cn/search?containerid=100103type%3D1%26t%3D10%26q%3D%236%E5%B2%81%E7%94%B7%E5%AD%A9%E8%8B%B1%E8%AF%AD%E9%98%BB%E6%AD%A2%E8%80%81%E5%A4%96%E6%99%AF%E5%8C%BA%E7%94%A8%E6%97%A0%E4%BA%BA%E6%9C%BA%23&isnewpage=1&extparam=seat%3D1%26filter_type%3Drealtimehot%26dgr%3D0%26cate%3D0%26pos%3D18%26realpos%3D18%26flag%3D1%26c_type%3D31%26display_time%3D1627448769%26pre_seqid%3D1627448769095023476113&luicode=10000011&lfid=106003type%3D25%26t%3D3%26disable_hot%3D1%26filter_type%3Drealtimehot","hot":1190125,"ads":false},{"title":"少女时代将完整体上综艺","category":"明星-日韩  ","description":"少女时代将完整体上综艺！时隔四年！期待了姐妹们！！！","url":"https://m.weibo.cn/search?containerid=100103type%3D1%26t%3D10%26q%3D%23%E5%B0%91%E5%A5%B3%E6%97%B6%E4%BB%A3%E5%B0%86%E5%AE%8C%E6%95%B4%E4%BD%93%E4%B8%8A%E7%BB%BC%E8%89%BA%23&isnewpage=1&extparam=seat%3D1%26filter_type%3Drealtimehot%26dgr%3D0%26cate%3D0%26pos%3D19%26realpos%3D19%26flag%3D1%26c_type%3D31%26display_time%3D1627448769%26pre_seqid%3D1627448769095023476113&luicode=10000011&lfid=106003type%3D25%26t%3D3%26disable_hot%3D1%26filter_type%3Drealtimehot","hot":1146872,"ads":false},{"title":"中国队夺冠的9个高燃瞬间","category":"体育  ","description":"新的一天开始了，昨日的成绩是今天前进的动力。期待中国队在新的比赛日继续努力拼搏，再登巅峰！","url":"https://m.weibo.cn/search?containerid=100103type%3D1%26t%3D10%26q%3D%23%E4%B8%AD%E5%9B%BD%E9%98%9F%E5%A4%BA%E5%86%A0%E7%9A%849%E4%B8%AA%E9%AB%98%E7%87%83%E7%9E%AC%E9%97%B4%23&isnewpage=1&extparam=seat%3D1%26filter_type%3Drealtimehot%26dgr%3D0%26cate%3D0%26pos%3D20%26realpos%3D20%26flag%3D1%26c_type%3D31%26display_time%3D1627448769%26pre_seqid%3D1627448769095023476113&luicode=10000011&lfid=106003type%3D25%26t%3D3%26disable_hot%3D1%26filter_type%3Drealtimehot","hot":1059736,"ads":false},{"title":"世界最贵炸薯条1300元一份","category":"社会  ","description":"近日，美国纽约一家餐厅推出了一道售价为200美元的炸薯条，约合人民币1297元，并获得吉尼斯世界纪录认证，成为世界上最贵的炸薯条。","url":"https://m.weibo.cn/search?containerid=100103type%3D1%26t%3D10%26q%3D%23%E4%B8%96%E7%95%8C%E6%9C%80%E8%B4%B5%E7%82%B8%E8%96%AF%E6%9D%A11300%E5%85%83%E4%B8%80%E4%BB%BD%23&isnewpage=1&extparam=seat%3D1%26filter_type%3Drealtimehot%26dgr%3D0%26cate%3D0%26pos%3D21%26realpos%3D21%26flag%3D1%26c_type%3D31%26display_time%3D1627448769%26pre_seqid%3D1627448769095023476113&luicode=10000011&lfid=106003type%3D25%26t%3D3%26disable_hot%3D1%26filter_type%3Drealtimehot","hot":991844,"ads":false},{"title":"陈梦扣杀","category":"体育  ","description":"陈梦以一个扣杀拿下第4局！！乒乓球女单比赛，@陈梦-乒乓球 在大比分0-2落后的情况下，将比分扳到2-2。","url":"https://m.weibo.cn/search?containerid=100103type%3D1%26t%3D10%26q%3D%23%E9%99%88%E6%A2%A6%E6%89%A3%E6%9D%80%23&isnewpage=1&extparam=seat%3D1%26filter_type%3Drealtimehot%26dgr%3D0%26cate%3D0%26pos%3D22%26realpos%3D22%26flag%3D1%26c_type%3D31%26display_time%3D1627448769%26pre_seqid%3D1627448769095023476113&luicode=10000011&lfid=106003type%3D25%26t%3D3%26disable_hot%3D1%26filter_type%3Drealtimehot","hot":989583,"ads":false},{"title":"南京7天内确诊超百例","category":"社会  ","description":"从7月20日－27日0时，南京市共报告了本土新冠肺炎感染者112例，此外还有14例南京关联病例，出现在南京以外的9个城市。","url":"https://m.weibo.cn/search?containerid=100103type%3D1%26t%3D10%26q%3D%23%E5%8D%97%E4%BA%AC7%E5%A4%A9%E5%86%85%E7%A1%AE%E8%AF%8A%E8%B6%85%E7%99%BE%E4%BE%8B%23&isnewpage=1&extparam=seat%3D1%26filter_type%3Drealtimehot%26dgr%3D0%26cate%3D0%26pos%3D23%26realpos%3D23%26flag%3D2%26c_type%3D31%26display_time%3D1627448769%26pre_seqid%3D1627448769095023476113&luicode=10000011&lfid=106003type%3D25%26t%3D3%26disable_hot%3D1%26filter_type%3Drealtimehot","hot":986034,"ads":false},{"title":"我到了你们人呢","category":"搞笑  ","description":"这个转播画面中，只有中国队一条艇啊，看不见别的队了！这就是中国速度！加油加油加油","url":"https://m.weibo.cn/search?containerid=100103type%3D1%26t%3D10%26q%3D%23%E6%88%91%E5%88%B0%E4%BA%86%E4%BD%A0%E4%BB%AC%E4%BA%BA%E5%91%A2%23&isnewpage=1&extparam=seat%3D1%26filter_type%3Drealtimehot%26dgr%3D0%26cate%3D0%26pos%3D24%26realpos%3D24%26flag%3D1%26c_type%3D31%26display_time%3D1627448769%26pre_seqid%3D1627448769095023476113&luicode=10000011&lfid=106003type%3D25%26t%3D3%26disable_hot%3D1%26filter_type%3Drealtimehot","hot":982664,"ads":false},{"title":"见过最佛系的乒乓球选手","category":"搞笑  ","description":"被泥哇笑死……真的打乒乓球一点方法都没有，完全就是随心情在打球哈哈哈哈哈哈哈！","url":"https://m.weibo.cn/search?containerid=100103type%3D1%26t%3D10%26q%3D%23%E8%A7%81%E8%BF%87%E6%9C%80%E4%BD%9B%E7%B3%BB%E7%9A%84%E4%B9%92%E4%B9%93%E7%90%83%E9%80%89%E6%89%8B%23&isnewpage=1&extparam=seat%3D1%26filter_type%3Drealtimehot%26dgr%3D0%26cate%3D0%26pos%3D25%26realpos%3D25%26flag%3D0%26c_type%3D31%26display_time%3D1627448769%26pre_seqid%3D1627448769095023476113&luicode=10000011&lfid=106003type%3D25%26t%3D3%26disable_hot%3D1%26filter_type%3Drealtimehot","hot":979473,"ads":false},{"title":"东京奥运会的纸板床裂了","category":"明星  ","description":"救命啊东京奥运会的纸板床裂了，该发生的还是发生了！","url":"https://m.weibo.cn/search?containerid=100103type%3D1%26t%3D10%26q%3D%23%E4%B8%9C%E4%BA%AC%E5%A5%A5%E8%BF%90%E4%BC%9A%E7%9A%84%E7%BA%B8%E6%9D%BF%E5%BA%8A%E8%A3%82%E4%BA%86%23&isnewpage=1&extparam=seat%3D1%26filter_type%3Drealtimehot%26dgr%3D0%26cate%3D0%26pos%3D26%26realpos%3D26%26flag%3D0%26c_type%3D31%26display_time%3D1627448769%26pre_seqid%3D1627448769095023476113&luicode=10000011&lfid=106003type%3D25%26t%3D3%26disable_hot%3D1%26filter_type%3Drealtimehot","hot":971779,"ads":false},{"title":"南京二级以上医院将全面推行预约挂号","category":"社会  ","description":"南京市卫健委副主任杨大锁介绍，当前，正值新冠肺炎疫情的特殊时期，为保障大家安全，除急诊、发热门诊外，二级以上医院全面推行预约挂号。严格限制探视、陪护。","url":"https://m.weibo.cn/search?containerid=100103type%3D1%26t%3D10%26q%3D%23%E5%8D%97%E4%BA%AC%E4%BA%8C%E7%BA%A7%E4%BB%A5%E4%B8%8A%E5%8C%BB%E9%99%A2%E5%B0%86%E5%85%A8%E9%9D%A2%E6%8E%A8%E8%A1%8C%E9%A2%84%E7%BA%A6%E6%8C%82%E5%8F%B7%23&isnewpage=1&extparam=seat%3D1%26filter_type%3Drealtimehot%26dgr%3D0%26cate%3D0%26pos%3D27%26realpos%3D27%26flag%3D1%26c_type%3D31%26display_time%3D1627448769%26pre_seqid%3D1627448769095023476113&luicode=10000011&lfid=106003type%3D25%26t%3D3%26disable_hot%3D1%26filter_type%3Drealtimehot","hot":966858,"ads":false},{"title":"才知道东京奥运会吉祥物长这样","category":"体育  ","description":"才知道东京奥运会吉祥物长这样，而且还要花5000日元才能合照，你会去合照吗？","url":"https://m.weibo.cn/search?containerid=100103type%3D1%26t%3D10%26q%3D%23%E6%89%8D%E7%9F%A5%E9%81%93%E4%B8%9C%E4%BA%AC%E5%A5%A5%E8%BF%90%E4%BC%9A%E5%90%89%E7%A5%A5%E7%89%A9%E9%95%BF%E8%BF%99%E6%A0%B7%23&isnewpage=1&extparam=seat%3D1%26filter_type%3Drealtimehot%26dgr%3D0%26cate%3D0%26pos%3D28%26realpos%3D28%26flag%3D1%26c_type%3D31%26display_time%3D1627448769%26pre_seqid%3D1627448769095023476113&luicode=10000011&lfid=106003type%3D25%26t%3D3%26disable_hot%3D1%26filter_type%3Drealtimehot","hot":960738,"ads":false},{"title":"奥运金牌榜","category":"体育  ","description":"奥运会金牌榜及奥运会金牌排名榜，从1896年第一届雅典奥运会到2016年第巴西里约奥运会。奥运会奖牌榜是依照国际奥林匹克委员会的官方排名榜排列,列出参与这届奥运会并获得奖牌的队伍与其所得的奖牌枚数,首先衡量金牌枚数的多少","url":"https://m.weibo.cn/search?containerid=100103type%3D1%26t%3D10%26q%3D%23%E5%A5%A5%E8%BF%90%E9%87%91%E7%89%8C%E6%A6%9C%23&isnewpage=1&extparam=seat%3D1%26filter_type%3Drealtimehot%26dgr%3D0%26cate%3D0%26pos%3D29%26realpos%3D29%26flag%3D0%26c_type%3D31%26display_time%3D1627448769%26pre_seqid%3D1627448769095023476113&luicode=10000011&lfid=106003type%3D25%26t%3D3%26disable_hot%3D1%26filter_type%3Drealtimehot","hot":865080,"ads":false},{"title":"海关在货物中发现多只活体黑寡妇","category":"社会  ","description":"近日，天津东疆海关查验人员在对一批进口集装箱货物进行现场查验时发现，多只活体“黑寡妇”。","url":"https://m.weibo.cn/search?containerid=100103type%3D1%26t%3D10%26q%3D%23%E6%B5%B7%E5%85%B3%E5%9C%A8%E8%B4%A7%E7%89%A9%E4%B8%AD%E5%8F%91%E7%8E%B0%E5%A4%9A%E5%8F%AA%E6%B4%BB%E4%BD%93%E9%BB%91%E5%AF%A1%E5%A6%87%23&isnewpage=1&extparam=seat%3D1%26filter_type%3Drealtimehot%26dgr%3D0%26cate%3D0%26pos%3D30%26realpos%3D30%26flag%3D1%26c_type%3D31%26display_time%3D1627448769%26pre_seqid%3D1627448769095023476113&luicode=10000011&lfid=106003type%3D25%26t%3D3%26disable_hot%3D1%26filter_type%3Drealtimehot","hot":820156,"ads":false},{"title":"邢菲说中国体操小花们最牛","category":"明星-内地  ","description":"刚刚邢菲发文安慰@LYF芦玉菲 并说:抱抱妹妹 你真的已经很棒了！摔倒之后还能继续完成比赛就已经赢了 在我心中你们就是冠军 唐茜靖  芦玉菲 章瑾 欧钰珊 中国体操小花们最牛！！🇨🇳","url":"https://m.weibo.cn/search?containerid=100103type%3D1%26t%3D10%26q%3D%23%E9%82%A2%E8%8F%B2%E8%AF%B4%E4%B8%AD%E5%9B%BD%E4%BD%93%E6%93%8D%E5%B0%8F%E8%8A%B1%E4%BB%AC%E6%9C%80%E7%89%9B%23&isnewpage=1&extparam=seat%3D1%26filter_type%3Drealtimehot%26dgr%3D0%26cate%3D0%26pos%3D31%26realpos%3D31%26flag%3D1%26c_type%3D31%26display_time%3D1627448769%26pre_seqid%3D1627448769095023476113&luicode=10000011&lfid=106003type%3D25%26t%3D3%26disable_hot%3D1%26filter_type%3Drealtimehot","hot":815416,"ads":false},{"title":"大连疫情","category":"社会  ","description":"社会  ","url":"https://m.weibo.cn/search?containerid=100103type%3D1%26t%3D10%26q%3D%E5%A4%A7%E8%BF%9E%E7%96%AB%E6%83%85&isnewpage=1&extparam=seat%3D1%26filter_type%3Drealtimehot%26dgr%3D0%26cate%3D0%26pos%3D32%26realpos%3D32%26flag%3D1%26c_type%3D31%26display_time%3D1627448769%26pre_seqid%3D1627448769095023476113&luicode=10000011&lfid=106003type%3D25%26t%3D3%26disable_hot%3D1%26filter_type%3Drealtimehot","hot":707798,"ads":false},{"title":"王简嘉禾泳帽下还藏着猫咪泳帽","category":"体育  ","description":"@王简嘉禾_靓靓 获得1500米自由泳第四名，比赛结束摘掉泳帽后，竟然又露出一个猫咪泳帽！","url":"https://m.weibo.cn/search?containerid=100103type%3D1%26t%3D10%26q%3D%23%E7%8E%8B%E7%AE%80%E5%98%89%E7%A6%BE%E6%B3%B3%E5%B8%BD%E4%B8%8B%E8%BF%98%E8%97%8F%E7%9D%80%E7%8C%AB%E5%92%AA%E6%B3%B3%E5%B8%BD%23&isnewpage=1&extparam=seat%3D1%26filter_type%3Drealtimehot%26dgr%3D0%26cate%3D0%26pos%3D33%26realpos%3D33%26flag%3D1%26c_type%3D31%26display_time%3D1627448769%26pre_seqid%3D1627448769095023476113&luicode=10000011&lfid=106003type%3D25%26t%3D3%26disable_hot%3D1%26filter_type%3Drealtimehot","hot":707791,"ads":false},{"title":"小区物业不得强制业主刷脸进出","category":"社会  ","description":"商家未经消费者同意擅自采集人脸信息进行数据分析、物业强制将人脸识别作为业主出入的唯一验证方式……《最高人民法院关于审理使用人脸识别技术处理个人信息相关民事案件适用法律若干问题的规定》28日公布，对经营场所滥用人脸识别技术、小区“刷脸”进门等问题作出明确规定。","url":"https://m.weibo.cn/search?containerid=100103type%3D1%26t%3D10%26q%3D%23%E5%B0%8F%E5%8C%BA%E7%89%A9%E4%B8%9A%E4%B8%8D%E5%BE%97%E5%BC%BA%E5%88%B6%E4%B8%9A%E4%B8%BB%E5%88%B7%E8%84%B8%E8%BF%9B%E5%87%BA%23&isnewpage=1&extparam=seat%3D1%26filter_type%3Drealtimehot%26dgr%3D0%26cate%3D0%26pos%3D34%26realpos%3D34%26flag%3D1%26c_type%3D31%26display_time%3D1627448769%26pre_seqid%3D1627448769095023476113&luicode=10000011&lfid=106003type%3D25%26t%3D3%26disable_hot%3D1%26filter_type%3Drealtimehot","hot":693520,"ads":false},{"title":"戴小雨奶奶遗嘱","category":"电视剧-国产剧  ","description":"戴小雨奶奶白静慧突然离世，提前留下的遗嘱让众人落泪！","url":"https://m.weibo.cn/search?containerid=100103type%3D1%26t%3D10%26q%3D%23%E6%88%B4%E5%B0%8F%E9%9B%A8%E5%A5%B6%E5%A5%B6%E9%81%97%E5%98%B1%23&isnewpage=1&extparam=seat%3D1%26filter_type%3Drealtimehot%26dgr%3D0%26cate%3D0%26pos%3D35%26realpos%3D35%26flag%3D1%26c_type%3D31%26display_time%3D1627448769%26pre_seqid%3D1627448769095023476113&luicode=10000011&lfid=106003type%3D25%26t%3D3%26disable_hot%3D1%26filter_type%3Drealtimehot","hot":498930,"ads":false},{"title":"TFBOYS八周年","category":"明星-内地  ","description":"明星-内地  ","url":"https://m.weibo.cn/search?containerid=100103type%3D1%26t%3D10%26q%3D%23TFBOYS%E5%85%AB%E5%91%A8%E5%B9%B4%23&isnewpage=1&extparam=seat%3D1%26filter_type%3Drealtimehot%26dgr%3D0%26cate%3D0%26pos%3D36%26realpos%3D36%26flag%3D1%26c_type%3D31%26display_time%3D1627448769%26pre_seqid%3D1627448769095023476113&luicode=10000011&lfid=106003type%3D25%26t%3D3%26disable_hot%3D1%26filter_type%3Drealtimehot","hot":449329,"ads":false},{"title":"微信里可以开借条了","category":"互联网  ","description":"#微信里可以开借条了#：提供规范模版、还款提醒等功能","url":"https://m.weibo.cn/search?containerid=100103type%3D1%26t%3D10%26q%3D%23%E5%BE%AE%E4%BF%A1%E9%87%8C%E5%8F%AF%E4%BB%A5%E5%BC%80%E5%80%9F%E6%9D%A1%E4%BA%86%23&isnewpage=1&extparam=seat%3D1%26filter_type%3Drealtimehot%26dgr%3D0%26cate%3D0%26pos%3D37%26realpos%3D37%26flag%3D1%26c_type%3D31%26display_time%3D1627448769%26pre_seqid%3D1627448769095023476113&luicode=10000011&lfid=106003type%3D25%26t%3D3%26disable_hot%3D1%26filter_type%3Drealtimehot","hot":388202,"ads":false},{"title":"张雨霏在泳池中比心","category":"体育  ","description":"@o张雨霏o 以2:04.89的成绩小组第一晋级决赛，一直保持着较大优势！比赛结束后，张雨霏在泳池中张雨霏对着镜头比心！","url":"https://m.weibo.cn/search?containerid=100103type%3D1%26t%3D10%26q%3D%23%E5%BC%A0%E9%9B%A8%E9%9C%8F%E5%9C%A8%E6%B3%B3%E6%B1%A0%E4%B8%AD%E6%AF%94%E5%BF%83%23&isnewpage=1&extparam=seat%3D1%26filter_type%3Drealtimehot%26dgr%3D0%26cate%3D0%26pos%3D38%26realpos%3D38%26flag%3D1%26c_type%3D31%26display_time%3D1627448769%26pre_seqid%3D1627448769095023476113&luicode=10000011&lfid=106003type%3D25%26t%3D3%26disable_hot%3D1%26filter_type%3Drealtimehot","hot":357280,"ads":false},{"title":"电焊工京广隧道泡水16小时救50多人","category":"社会  ","description":"7月20日，来自湖北十堰的电焊工袁格兵在郑州市京广北路隧道的大水中救出50多个人，期间他在水里泡了16个小时，只吃了几口馒头。","url":"https://m.weibo.cn/search?containerid=100103type%3D1%26t%3D10%26q%3D%23%E7%94%B5%E7%84%8A%E5%B7%A5%E4%BA%AC%E5%B9%BF%E9%9A%A7%E9%81%93%E6%B3%A1%E6%B0%B416%E5%B0%8F%E6%97%B6%E6%95%9150%E5%A4%9A%E4%BA%BA%23&isnewpage=1&extparam=seat%3D1%26filter_type%3Drealtimehot%26dgr%3D0%26cate%3D0%26pos%3D39%26realpos%3D39%26flag%3D1%26c_type%3D31%26display_time%3D1627448769%26pre_seqid%3D1627448769095023476113&luicode=10000011&lfid=106003type%3D25%26t%3D3%26disable_hot%3D1%26filter_type%3Drealtimehot","hot":240997,"ads":false},{"title":"上交祝贺女子赛艇四人双桨夺金","category":"校园  ","description":"在刚刚结束的东京奥运会赛艇女子四人双桨决赛上，中国组合赛艇女子四人双桨夺金；上海交通大学发博祝贺学子陈云霞 、张灵 ，以及搭档吕扬、崔晓桐为中国队摘得本届奥运会第10枚金牌！祝贺姑娘们！","url":"https://m.weibo.cn/search?containerid=100103type%3D1%26t%3D10%26q%3D%23%E4%B8%8A%E4%BA%A4%E7%A5%9D%E8%B4%BA%E5%A5%B3%E5%AD%90%E8%B5%9B%E8%89%87%E5%9B%9B%E4%BA%BA%E5%8F%8C%E6%A1%A8%E5%A4%BA%E9%87%91%23&isnewpage=1&extparam=seat%3D1%26filter_type%3Drealtimehot%26dgr%3D0%26cate%3D0%26pos%3D40%26realpos%3D40%26flag%3D1%26c_type%3D31%26display_time%3D1627448769%26pre_seqid%3D1627448769095023476113&luicode=10000011&lfid=106003type%3D25%26t%3D3%26disable_hot%3D1%26filter_type%3Drealtimehot","hot":239690,"ads":false},{"title":"美国实际新冠感染人数或被低估60%","category":"社会  ","description":"当地时间7月26日，《美国国家科学院院刊》发文称，美国华盛顿大学的研究员们发现，由于一些包括检测偏差、延迟报告在内的重大缺陷，全美实际的新冠病例数量可能被低估了60%之多。","url":"https://m.weibo.cn/search?containerid=100103type%3D1%26t%3D10%26q%3D%23%E7%BE%8E%E5%9B%BD%E5%AE%9E%E9%99%85%E6%96%B0%E5%86%A0%E6%84%9F%E6%9F%93%E4%BA%BA%E6%95%B0%E6%88%96%E8%A2%AB%E4%BD%8E%E4%BC%B060%25%23&isnewpage=1&extparam=seat%3D1%26filter_type%3Drealtimehot%26dgr%3D0%26cate%3D0%26pos%3D41%26realpos%3D41%26flag%3D1%26c_type%3D31%26display_time%3D1627448769%26pre_seqid%3D1627448769095023476113&luicode=10000011&lfid=106003type%3D25%26t%3D3%26disable_hot%3D1%26filter_type%3Drealtimehot","hot":236450,"ads":false},{"title":"南京医护三级防护为黄码产妇接生","category":"社会  ","description":"7月25日，南京溧水一名“黄码”妈妈小君临产，被送往溧水区人民医院。由于小君是“黄码”人员，所有参与人员均三级防护。经历了三个小时的分娩过程，医护人员的防护服已被汗水浸透，护目镜上雾气蒙蒙。终于，在大家的努力下，小君顺利分娩，母子平安！","url":"https://m.weibo.cn/search?containerid=100103type%3D1%26t%3D10%26q%3D%23%E5%8D%97%E4%BA%AC%E5%8C%BB%E6%8A%A4%E4%B8%89%E7%BA%A7%E9%98%B2%E6%8A%A4%E4%B8%BA%E9%BB%84%E7%A0%81%E4%BA%A7%E5%A6%87%E6%8E%A5%E7%94%9F%23&isnewpage=1&extparam=seat%3D1%26filter_type%3Drealtimehot%26dgr%3D0%26cate%3D0%26pos%3D42%26realpos%3D42%26flag%3D1%26c_type%3D31%26display_time%3D1627448769%26pre_seqid%3D1627448769095023476113&luicode=10000011&lfid=106003type%3D25%26t%3D3%26disable_hot%3D1%26filter_type%3Drealtimehot","hot":233912,"ads":false},{"title":"杨倩妈妈说女儿是单身","category":"体育  ","description":"体育  ","url":"https://m.weibo.cn/search?containerid=100103type%3D1%26t%3D10%26q%3D%23%E6%9D%A8%E5%80%A9%E5%A6%88%E5%A6%88%E8%AF%B4%E5%A5%B3%E5%84%BF%E6%98%AF%E5%8D%95%E8%BA%AB%23&isnewpage=1&extparam=seat%3D1%26filter_type%3Drealtimehot%26dgr%3D0%26cate%3D0%26pos%3D43%26realpos%3D43%26flag%3D1%26c_type%3D31%26display_time%3D1627448769%26pre_seqid%3D1627448769095023476113&luicode=10000011&lfid=106003type%3D25%26t%3D3%26disable_hot%3D1%26filter_type%3Drealtimehot","hot":231065,"ads":false},{"title":"七成95后农民工渴望职业培训","category":"社会  ","description":"这届农民工很上进！对外经济贸易大学教育与开放经济研究中心、工人日报、蚂蚁集团研究院、58同城联合发布的《2021新生代农民工职业技能调研报告》显示，七成95后农民工渴望职业培训。","url":"https://m.weibo.cn/search?containerid=100103type%3D1%26t%3D10%26q%3D%23%E4%B8%83%E6%88%9095%E5%90%8E%E5%86%9C%E6%B0%91%E5%B7%A5%E6%B8%B4%E6%9C%9B%E8%81%8C%E4%B8%9A%E5%9F%B9%E8%AE%AD%23&isnewpage=1&extparam=seat%3D1%26filter_type%3Drealtimehot%26dgr%3D0%26cate%3D0%26pos%3D44%26realpos%3D44%26flag%3D1%26c_type%3D31%26display_time%3D1627448769%26pre_seqid%3D1627448769095023476113&luicode=10000011&lfid=106003type%3D25%26t%3D3%26disable_hot%3D1%26filter_type%3Drealtimehot","hot":225301,"ads":false},{"title":"众星缅怀唐山大地震逝世者","category":"明星-内地  ","description":"1976年7月28日，一场7.8级的强震，让24.2万同胞遇难。45年了，时间会慢慢抚平伤痛，却抚不去思念与记忆。让我们再一次缅怀逝者，致敬重生，愿山河无恙，人间皆安！ ​​​","url":"https://m.weibo.cn/search?containerid=100103type%3D1%26t%3D10%26q%3D%23%E4%BC%97%E6%98%9F%E7%BC%85%E6%80%80%E5%94%90%E5%B1%B1%E5%A4%A7%E5%9C%B0%E9%9C%87%E9%80%9D%E4%B8%96%E8%80%85%23&isnewpage=1&extparam=seat%3D1%26filter_type%3Drealtimehot%26dgr%3D0%26cate%3D0%26pos%3D45%26realpos%3D45%26flag%3D0%26c_type%3D31%26display_time%3D1627448769%26pre_seqid%3D1627448769095023476113&luicode=10000011&lfid=106003type%3D25%26t%3D3%26disable_hot%3D1%26filter_type%3Drealtimehot","hot":224351,"ads":false},{"title":"天官赐福","category":"动漫-国产动漫  ","description":"动漫-国产动漫  ","url":"https://m.weibo.cn/search?containerid=100103type%3D1%26t%3D10%26q%3D%E5%A4%A9%E5%AE%98%E8%B5%90%E7%A6%8F&isnewpage=1&extparam=seat%3D1%26filter_type%3Drealtimehot%26dgr%3D0%26cate%3D0%26pos%3D46%26realpos%3D46%26flag%3D1%26c_type%3D31%26display_time%3D1627448769%26pre_seqid%3D1627448769095023476113&luicode=10000011&lfid=106003type%3D25%26t%3D3%26disable_hot%3D1%26filter_type%3Drealtimehot","hot":218682,"ads":false},{"title":"体现奥运格局的瞬间","category":"情感  ","description":"她用健壮的身躯  为祖国带来了荣耀，她用温柔的内心  展现了大国的风范。她是侯志慧！👍格局不是每个人都有的","url":"https://m.weibo.cn/search?containerid=100103type%3D1%26t%3D10%26q%3D%23%E4%BD%93%E7%8E%B0%E5%A5%A5%E8%BF%90%E6%A0%BC%E5%B1%80%E7%9A%84%E7%9E%AC%E9%97%B4%23&isnewpage=1&extparam=seat%3D1%26filter_type%3Drealtimehot%26dgr%3D0%26cate%3D0%26pos%3D47%26realpos%3D47%26flag%3D1%26c_type%3D31%26display_time%3D1627448769%26pre_seqid%3D1627448769095023476113&luicode=10000011&lfid=106003type%3D25%26t%3D3%26disable_hot%3D1%26filter_type%3Drealtimehot","hot":216765,"ads":false},{"title":"李佳琦下班后的幸福","category":"明星  ","description":"李佳琦凌晨发博：这就是下班后的幸福 我们never有小枕头和凉感垫 佩奇只有冰皮被[允悲] ​​​​ Never和佩奇超可爱啊 ​","url":"https://m.weibo.cn/search?containerid=100103type%3D1%26t%3D10%26q%3D%23%E6%9D%8E%E4%BD%B3%E7%90%A6%E4%B8%8B%E7%8F%AD%E5%90%8E%E7%9A%84%E5%B9%B8%E7%A6%8F%23&isnewpage=1&extparam=seat%3D1%26filter_type%3Drealtimehot%26dgr%3D0%26cate%3D0%26pos%3D48%26realpos%3D48%26flag%3D0%26c_type%3D31%26display_time%3D1627448769%26pre_seqid%3D1627448769095023476113&luicode=10000011&lfid=106003type%3D25%26t%3D3%26disable_hot%3D1%26filter_type%3Drealtimehot","hot":214468,"ads":false},{"title":"郑州奔驰堵了全车库","category":"社会  ","description":"郑州特大暴雨当天，一小区地下停车场被淹，黑色奔驰车堵了全车库！","url":"https://m.weibo.cn/search?containerid=100103type%3D1%26t%3D10%26q%3D%23%E9%83%91%E5%B7%9E%E5%A5%94%E9%A9%B0%E5%A0%B5%E4%BA%86%E5%85%A8%E8%BD%A6%E5%BA%93%23&isnewpage=1&extparam=seat%3D1%26filter_type%3Drealtimehot%26dgr%3D0%26cate%3D0%26pos%3D49%26realpos%3D49%26flag%3D0%26c_type%3D31%26display_time%3D1627448769%26pre_seqid%3D1627448769095023476113&luicode=10000011&lfid=106003type%3D25%26t%3D3%26disable_hot%3D1%26filter_type%3Drealtimehot","hot":213976,"ads":false},{"title":"河南洪灾区到底急需什么","category":"社会  ","description":"在洪灾头两天，居民们主要需求是方便面、瓶装水等基本生活物资。但在居民不断转移到安置点、民间救援队还在不断抢险救援的当下，来自灾区的求援内容开始变得多样","url":"https://m.weibo.cn/search?containerid=100103type%3D1%26t%3D10%26q%3D%23%E6%B2%B3%E5%8D%97%E6%B4%AA%E7%81%BE%E5%8C%BA%E5%88%B0%E5%BA%95%E6%80%A5%E9%9C%80%E4%BB%80%E4%B9%88%23&isnewpage=1&extparam=seat%3D1%26filter_type%3Drealtimehot%26dgr%3D0%26cate%3D0%26pos%3D50%26realpos%3D50%26flag%3D1%26c_type%3D31%26display_time%3D1627448769%26pre_seqid%3D1627448769095023476113&luicode=10000011&lfid=106003type%3D25%26t%3D3%26disable_hot%3D1%26filter_type%3Drealtimehot","hot":212283,"ads":false}]